{
  "id": "common-responses-reassurance-u5-10",
  "title": "Common Responses: Reassurance (Usefulness 5-10)",
  "description": "Traveler usefulness 5-10/10 phrases for the Reassurance subcategory within Common Responses. Includes 5 card(s).",
  "cards": [
    {
      "english": "That's fine.",
      "romaji": "Iie iie.",
      "japanese": "いいえいいえ。"
    },
    {
      "english": "Don't worry about it.",
      "romaji": "Iie iie.",
      "japanese": "いいえいいえ。"
    },
    {
      "english": "No, no, that's fine.",
      "romaji": "Iie, iie.",
      "japanese": "いいえ、いいえ。"
    },
    {
      "english": "Don't worry about it.",
      "romaji": "Iie, iie.",
      "japanese": "いいえ、いいえ。"
    },
    {
      "english": "It's okay.",
      "romaji": "Daijobu.",
      "japanese": "大丈夫。"
    }
  ]
}
