{
  "id": "health-pain-ailments-u5-10",
  "title": "Health: Pain / Ailments (Usefulness 5-10)",
  "description": "Traveler usefulness 5-10/10 phrases for the Pain / Ailments subcategory within Health. Includes 6 card(s).",
  "cards": [
    {
      "english": "My stomach hurts.",
      "romaji": "Onaka ga itai desu.",
      "japanese": "お腹が痛いです。"
    },
    {
      "english": "My head hurts.",
      "romaji": "Atama ga itai desu.",
      "japanese": "頭が痛いです。"
    },
    {
      "english": "I have a headache.",
      "romaji": "Atama ga itai desu.",
      "japanese": "頭が痛いです。"
    },
    {
      "english": "I have a sore throat.",
      "romaji": "Nodo ga itai desu.",
      "japanese": "喉が痛いです。"
    },
    {
      "english": "Ouch!",
      "romaji": "Itai!",
      "japanese": "痛い！"
    },
    {
      "english": "My throat hurts.",
      "romaji": "Nodo ga itai desu.",
      "japanese": "喉が痛いです。"
    }
  ]
}
