{
  "id": "shopping-clothing-u7",
  "title": "Shopping: Clothing (Usefulness 7)",
  "description": "Traveler usefulness 7/10 phrases for the Clothing subcategory within Shopping. Includes 4 card(s).",
  "cards": [
    {
      "english": "I like kimonos.",
      "romaji": "Watashi wa kimono ga suki desu.",
      "japanese": "私は着物が好きです。"
    },
    {
      "english": "Where can I buy Japanese socks?",
      "romaji": "Tabi wa doko de kaemasuka?",
      "japanese": "足袋はどこで買えますか？"
    },
    {
      "english": "Where can I buy Japanese sandals?",
      "romaji": "Zori wa doko de kaemasuka?",
      "japanese": "草履はどこで買えますか？"
    },
    {
      "english": "Do you have a yukata?",
      "romaji": "Yukata ga arimasu ka.",
      "japanese": "浴衣がありますか。"
    }
  ]
}
